ddconst/__init__.py
ddconst/plotting/__init__.py
ddconst/plotting/colors.py
ddconst-0.0.3.dist-info/licenses/LICENSE
ddconst-0.0.3.dist-info/METADATA
ddconst-0.0.3.dist-info/WHEEL
ddconst-0.0.3.dist-info/top_level.txt
ddconst-0.0.3.dist-info/RECORD
